ads_api/__init__.py
ads_api/app.py
ads_api/config.py
ads_api/credentials.py
ads_api/azure/__init__.py
ads_api/azure/azure_credentials.py
ads_api/bing/__init__.py
ads_api/bing/active_accounts.py
ads_api/bing/download_helpers.py
ads_api/bing/campaign_management/__init__.py
ads_api/bing/campaign_management/campaign_management.py
ads_api/bing/reporting/__init__.py
ads_api/bing/reporting/reporting_helpers.py
ads_api/bing/reporting/jobs/__init__.py
ads_api/bing/reporting/jobs/download_campaign_adgroups.py
ads_api/bing/reporting/jobs/download_keyword_performance_to_azure.py
ads_api/bing/reporting/report_request/__init__.py
ads_api/bing/reporting/report_request/account_performance.py
ads_api/bing/reporting/report_request/budget_performance.py
ads_api/bing/reporting/report_request/campaign_performance.py
ads_api/bing/reporting/report_request/change_history.py
ads_api/bing/reporting/report_request/keyword_performance.py
ads_api/bing/reporting/report_to_dataframe/__init__.py
ads_api/bing/reporting/report_to_dataframe/dealer_config.py
ads_api/bing/reporting/report_to_dataframe/keyword_performance.py
ads_api/database/__init__.py
ads_api/database/dealer_config.py
ads_api/database/get_dealer_config.py
ads_api/google/__init__.py
ads_api/google/google_adwords.py
ads_api/google/utils.py
ads_api/google/reporting/__init__.py
ads_api/google/reporting/report_to_dataframe/__init__.py
ads_api/google/reporting/report_to_dataframe/adgroup_performance.py
ads_api/google/reporting/report_to_dataframe/keyword_performance.py
ads_api-0.1.7.5.dist-info/METADATA
ads_api-0.1.7.5.dist-info/WHEEL
ads_api-0.1.7.5.dist-info/top_level.txt
ads_api-0.1.7.5.dist-info/RECORD
